silit/__init__.py
silit/commands.py
silit/templates/project/build.py
silit/templates/project/setup.py
silit/templates/project/silit.py
silit/templates/project/app/__init__.py
silit/templates/project/config/config.py
silit/templates/project/public/index.py
silit/templates/project/routes/web.py
silit-0.1.0.dist-info/METADATA
silit-0.1.0.dist-info/WHEEL
silit-0.1.0.dist-info/entry_points.txt
silit-0.1.0.dist-info/top_level.txt
silit-0.1.0.dist-info/RECORD
